README.md
setup.py
netcity_volga/__init__.py
netcity_volga/client.py
netcity_volga/errors.py
netcity_volga/models.py
netcity_volga.egg-info/PKG-INFO
netcity_volga.egg-info/SOURCES.txt
netcity_volga.egg-info/dependency_links.txt
netcity_volga.egg-info/requires.txt
netcity_volga.egg-info/top_level.txt