Metadata-Version: 2.1
Name: netcity-volga
Version: 1.0
Summary: UNKNOWN
Home-page: https://github.com/tulen34/netcity-volga
Author-email: pulsar04040@gmail.com
License: MIT
Platform: UNKNOWN
Requires-Python: >=3.9
